{
  "ticker": "ASMS.NS",
  "company": "Avio Smart Market Stack Limited",
  "date": "2026-07-09",
  "generated_at_utc": "2026-07-09T08:29:26.918610+00:00",
  "fmp": "============================================================\nVERIFIED FUNDAMENTAL DATA  (Source: Financial Modeling Prep)\n============================================================\n\n============================================================",
  "screener": "=== Screener.in: ASMS ===\nAbout: \nQuarterly Results (last 4Q — Mar 2023 / Mar 2025 / Dec 2025 / Mar 2026):\n  Sales +: 12.05 | 8.91 | 48.34 | 34.39\n  Net Profit +: 439.88 | 0.93 | 2.45 | 2.08\n  EPS in Rs: 14.44 | 0.03 | 0.08 | 0.07\nAnnual P&L (Mar 2021 / Mar 2022 / Mar 2023 / Mar 2025 / Mar 2026):\n  Sales +: 63 | 65 | 52 | 40 | 104\n  OPM %: 9% | 9% | 4% | -1% | 5%\n  Net Profit +: -49 | -50 | 412 | 2 | 6\n  EPS in Rs: -14.46 | -14.77 | 13.54 | 0.06 | 0.20\nBalance Sheet (last 3 years):\n  Reserves: 498 | -2 | 4\n  Borrowings +: 0 | 0 | 9\n  Total Assets: 750 | 33 | 68\nShareholding Pattern (latest):\n  Promoters +: 67.50% (prev: 69.37%)\n  FIIs +: 1.67% (prev: 1.68%)\n  DIIs +: 0.22%\n  Public +: 30.62% (prev: 28.74%)",
  "yfinance": "=== yfinance Fundamentals: ASMS.NS ===\nProfile: Sector=Technology | Industry=Information Technology Services | Exchange=NSI | 52W=[Rs7–Rs18] | AvgVol=1,091,642\nAnalyst: Consensus=None\nValuation: P/E (TTM)=37.37x | P/B=6.18x | EV/EBITDA=38.74x | EV/Revenue=2.12x\nEarnings: EPS (TTM)=Rs0.19 | EPS Growth=133.30% | Rev Growth=286.10%\nProfitability: Gross Margin=8.46% | Op Margin=6.59% | Net Margin=5.71% | ROE=19.02% | ROA=6.88%\nBalance Sheet: D/E=0.26x | Current Ratio=1.39x | Quick Ratio=1.37x | Free CF=Rs-0 Cr | Op CF=Rs1 Cr\nMarket: Mkt Cap=Rs216 Cr | Ent Value=Rs220 Cr | Beta=0.26x\nBusiness: Avio Smart Market Stack Limited provides automatic identification, data capture, and financial inclusion services in India and internationally. The company offers a range of banking services, including financial inclusion, business correspondent, and business facilitation banking services. It also provides e-government solutions that include health…",
  "announcements": "",
  "news_yf": "",
  "news_web": "- Avio Smart Market Stack Limited (ASMS.NS) Stock Price, News, Quote & History - Yahoo Finance (https://finance.yahoo.com/quote/ASMS.NS)\n- Avio Smart Market Stack Ltd. Share Price Today (https://zerodha.com/markets/stocks/NSE/ASMS)\n- Avio Smart Market Stack (NSEI:ASMS) Stock Price (https://simplywall.st/stock/nsei/asms)\n- Avio Smart Market Stack Limited Share Price - Stocks (https://www.kotakneo.com/stocks/bartronics-india-share-price)\n- ASMS | Avio Smart Market Stack Ltd | Stock Overview (https://www.morningstar.in/stocks/0p0000bbhf/NSE-Avio-Smart-Market-Stack-Ltd/overview.aspx)\n- Avio Smart Market Stack Limited | Powering India’s Rural Transformation (https://www.bartronics.com)",
  "earnings": "",
  "analyst": "",
  "profile": "",
  "macro": {
    "fred": "============================================================\nGLOBAL MACRO INDICATORS  (Source: FRED — Federal Reserve)\nAs of 09 July 2026\n============================================================\n\nBrent Crude Oil [2026-07-06]\n  Current: 69.56 USD/bbl  (+1.28% vs prior)\n  India impact: Higher crude → India CAD widens, rupee weakens, oil companies pressured; lower crude → opposite\n\nUS Dollar Index (DXY) [2026-07-02]\n  Current: 120.69  (-0.38% vs prior)\n  India impact: Stronger DXY → FII outflows from India, rupee weakens; weaker DXY → FII inflows rise\n\nFed Funds Rate [2026-07-07]\n  Current: 3.63 %  (+0.00% vs prior)\n  India impact: Higher Fed rate → capital flows to USD, EM selling pressure; cuts → EM relief rally\n\nCBOE VIX [2026-07-07]\n  Current: 16.13  (+3.60% vs prior)\n  India impact: High VIX → risk-off, FII sell EMs including India; low VIX → risk-on, inflows\n\nUS 10Y Treasury Yield [2026-06-01]\n  Current: 4.47 %\n  India impact: Rising US 10Y → India bonds less attractive, FII debt outflows; falling → inflows\n\nYield Curve (10Y-2Y) [2026-07-08]\n  Current: 0.35 %  (-2.78% vs prior)\n  India impact: Negative spread = inverted curve = US recession risk → global risk-off, India hit\n\n============================================================",
    "india": "============================================================\nINDIA MACRO DATA  (Sources: NSE, RBI, yfinance)\nAs of 09 July 2026\n============================================================\n\n[MARKET RATES]\n  USD/INR           : Rs.95.32  (-0.23% — rupee stronger vs USD)\n  India impact      : Stronger rupee reduces import costs, supports FII inflows\n  Nifty 50          : 24,051.15  (+0.64% today)\n\n[RBI MONETARY POLICY]\n  Repo Rate         : 6.25% (last known)\n  SDF (floor)       : 6.00%\n  MSF / Bank Rate   : 6.50%\n  CRR               : 4.00%\n  Stance            : Neutral\n  Last updated      : fallback as of Jul 2026\n  India impact      : Repo at 6.25% — accommodative relative to historic norms; supports credit growth\n\n[FII / DII DAILY FLOWS — Cash Market]\n  Data unavailable — NSE session could not be established\n  (Check NSE website directly for FII/DII flows)\n\n============================================================",
    "world_bank": "World Bank (latest annual):\n  Real GDP growth %: India 7.6% (2025) · US 2.2% (2025) · World 2.9% (2025)\n  Inflation (CPI) %: India 2.4% (2025) · World 3.0% (2025)",
    "finnhub": ""
  }
}