{
  "ticker": "DIAMONDYD.NS",
  "company": "Prataap Snacks Limited",
  "date": "2026-07-07",
  "generated_at_utc": "2026-07-07T12:40:05.661830+00:00",
  "fmp": "============================================================\nVERIFIED FUNDAMENTAL DATA  (Source: Financial Modeling Prep)\n============================================================\n\n============================================================",
  "screener": "=== Screener.in: DIAMONDYD ===\nAbout: \nQuarterly Results (last 4Q — Jun 2022 / Sep 2022 / Dec 2022 / Mar 2023):\n  Sales +: 383 | 457 | 426 | 387\n  Net Profit +: -11 | 4 | 5 | 22\n  EPS in Rs: -4.86 | 1.81 | 2.24 | 9.21\nAnnual P&L (Mar 2019 / Mar 2020 / Mar 2021 / Mar 2022 / Mar 2023):\n  Sales +: 1,171 | 1,394 | 1,171 | 1,397 | 1,653\n  OPM %: 7% | 7% | 5% | 4% | 4%\n  Net Profit +: 45 | 47 | 14 | 3 | 20\n  EPS in Rs: 19.03 | 20.01 | 6.04 | 1.24 | 8.66\nBalance Sheet (last 3 years):\n  Reserves: 611 | 613 | 665\n  Borrowings +: 57 | 80 | 60\n  Total Assets: 886 | 907 | 912\nShareholding Pattern (latest):\n  Promoters +: 55.59% (prev: 54.81%)\n  FIIs +: 4.79% (prev: 5.02%)\n  DIIs +: 7.21%\n  Public +: 32.41% (prev: 32.96%)",
  "yfinance": "=== yfinance Fundamentals: DIAMONDYD.NS ===\nProfile: Sector=Consumer Defensive | Industry=Packaged Foods | Exchange=NSI | 52W=[Rs859–Rs1,229] | AvgVol=70,297\nAnalyst: Target(mean)=Rs1,148 | Target(high)=Rs1,350 | Target(low)=Rs945 | Consensus=None | Analysts=2\nValuation: P/E (TTM)=301.01x | P/E (Fwd)=45.71x | P/B=4.15x | EV/EBITDA=34.71x | EV/Revenue=1.65x\nEarnings: EPS (TTM)=Rs4.07 | EPS (Fwd)=Rs26.80 | Rev Growth=4.90%\nProfitability: Gross Margin=28.83% | Op Margin=0.88% | Net Margin=0.56% | ROE=1.40% | ROA=0.99%\nBalance Sheet: D/E=0.06x | Current Ratio=1.94x | Quick Ratio=0.74x | Free CF=Rs60 Cr | Op CF=Rs50 Cr\nMarket: Mkt Cap=Rs2,928 Cr | Ent Value=Rs2,839 Cr | Beta=0.03x | Div Yield=4.00%\nBusiness: Prataap Snacks Limited manufactures and sells packaged snacks in India and internationally. It offers chips, extruded snacks, namkeen, and pellets, as well as buns, cakes, cookies, sweet snacks, and popcorn under the Yellow Diamond and Avadh brands. The company sells its products through distributors, independent grocers, and retail stores. Prataap…",
  "announcements": "",
  "news_yf": "",
  "news_web": "- Prataap Snacks Limited (INE393P01035) - NSE (https://www.nseindia.com/get-quote/equity/DIAMONDYD/Prataap-Snacks-Limited)\n- [PDF] Prataap Snacks Limited - Yellow Diamond (https://www.yellowdiamond.in/wp-content/uploads/2024/09/Intimation-Detailed-Public-Statement.pdf)\n- Prataap Snacks Limited (DIAMONDYD.BO) Stock Price, News ... (https://finance.yahoo.com/quote/DIAMONDYD.BO)\n- Prataap Snacks Limited (NSE:DIAMONDYD) Just Released Its Third ... (https://simplywall.st/stocks/in/food-beverage-tobacco/nse-diamondyd/prataap-snacks-shares/news/prataap-snacks-limited-nsediamondyd-just-released-its-third)\n- Prataap Snacks Ltd - Sharekhan (https://www.sharekhan.com/stock/prataap-snacks-ltd)\n- India's competition watchdog approves majority stake sale ... - Reuters (https://www.reuters.com/business/retail-consumer/indias-competition-watchdog-approves-majority-stake-sale-prataap-snacks-2024-12-31)",
  "earnings": "",
  "analyst": "",
  "profile": "",
  "macro": {
    "fred": "============================================================\nGLOBAL MACRO INDICATORS  (Source: FRED — Federal Reserve)\nAs of 07 July 2026\n============================================================\n\nBrent Crude Oil [2026-06-29]\n  Current: 71.59 USD/bbl  (+2.04% vs prior)\n  India impact: Higher crude → India CAD widens, rupee weakens, oil companies pressured; lower crude → opposite\n\nUS Dollar Index (DXY) [2026-07-02]\n  Current: 120.69  (-0.38% vs prior)\n  India impact: Stronger DXY → FII outflows from India, rupee weakens; weaker DXY → FII inflows rise\n\nFed Funds Rate [2026-07-03]\n  Current: 3.63 %  (+0.00% vs prior)\n  India impact: Higher Fed rate → capital flows to USD, EM selling pressure; cuts → EM relief rally\n\nCBOE VIX [2026-07-03]\n  Current: 15.81  (-2.11% vs prior)\n  India impact: High VIX → risk-off, FII sell EMs including India; low VIX → risk-on, inflows\n\nUS 10Y Treasury Yield [2026-06-01]\n  Current: 4.47 %\n  India impact: Rising US 10Y → India bonds less attractive, FII debt outflows; falling → inflows\n\nYield Curve (10Y-2Y) [2026-07-06]\n  Current: 0.35 %  (+0.00% vs prior)\n  India impact: Negative spread = inverted curve = US recession risk → global risk-off, India hit\n\n============================================================",
    "india": "============================================================\nINDIA MACRO DATA  (Sources: NSE, RBI, yfinance)\nAs of 07 July 2026\n============================================================\n\n[MARKET RATES]\n  USD/INR           : Rs.94.97  (-0.43% — rupee stronger vs USD)\n  India impact      : Stronger rupee reduces import costs, supports FII inflows\n  Nifty 50          : 24,398.70  (-0.10% today)\n\n[RBI MONETARY POLICY]\n  Repo Rate         : 6.25% (last known)\n  SDF (floor)       : 6.00%\n  MSF / Bank Rate   : 6.50%\n  CRR               : 4.00%\n  Stance            : Neutral\n  Last updated      : fallback as of Jul 2026\n  India impact      : Repo at 6.25% — accommodative relative to historic norms; supports credit growth\n\n[FII / DII DAILY FLOWS — Cash Market]\n  Data unavailable — NSE session could not be established\n  (Check NSE website directly for FII/DII flows)\n\n============================================================",
    "world_bank": "World Bank (latest annual):\n  Real GDP growth %: India 7.6% (2025) · World 2.9% (2025)\n  Inflation (CPI) %: US 2.9% (2024) · World 3.0% (2025)",
    "finnhub": ""
  }
}