{
  "ticker": "GFSTEELS.NS",
  "company": "Grand Foundry Limited",
  "date": "2026-07-13",
  "generated_at_utc": "2026-07-13T08:18:46.043427+00:00",
  "fmp": "============================================================\nVERIFIED FUNDAMENTAL DATA  (Source: Financial Modeling Prep)\n============================================================\n\n============================================================",
  "screener": "=== Screener.in: GFSTEELS ===\nAbout: \nQuarterly Results (last 4Q — ):\n  Sales +: \n  Net Profit +: \n  EPS in Rs: \nAnnual P&L (Mar 2006 9m / Mar 2007 / Mar 2008 / Mar 2009 / Mar 2010):\n  Sales +: 1 | 0 | 0 | 0 | 3\n  OPM %: -975% |  | -440% | -71% | -26%\n  Net Profit +: 20 | 17 | -4 | -1 | 10\n  EPS in Rs:  |  |  |  | \nBalance Sheet (last 3 years):\n  Reserves: -24 | -25 | -15\n  Borrowings +: 21 | 22 | 13\n  Total Assets: 11 | 10 | 13\nShareholding Pattern (latest):\n  Promoters +: 70.18%\n  DIIs +: 0.03%\n  Public +: 29.81% (prev: 29.79%)\n  No. of Shareholders: 23,106 (prev: 23,181)",
  "yfinance": "=== yfinance Fundamentals: GFSTEELS.NS ===\nProfile: Sector=Basic Materials | Industry=Steel | Exchange=NSI | 52W=[Rs10–Rs14] | AvgVol=750\nAnalyst: Consensus=None\nValuation: P/E (TTM)=238.17x | P/B=-7.97x | EV/Revenue=4.57x\nEarnings: EPS (TTM)=Rs0.06 | Rev Growth=51,244.40%\nProfitability: Gross Margin=13.02% | Op Margin=10.24% | Net Margin=1.72% | ROA=6.95%\nBalance Sheet: Current Ratio=1.11x | Quick Ratio=1.04x | Free CF=Rs-1 Cr | Op CF=Rs-1 Cr\nMarket: Mkt Cap=Rs43 Cr | Ent Value=Rs48 Cr | Beta=-0.51x\nBusiness: Grand Foundry Limited manufactures, exports, and sells bright steel bars in India, the United States, Japan, Singapore, Italy, Australia, and Canada. It also offers pickling and heat treatment lines. Grand Foundry Limited was incorporated in 1973 and is based in Mumbai, India.",
  "announcements": "",
  "news_yf": "",
  "news_web": "- Grand Foundry Live Share Price, Stock Analysis and ... (https://trendlyne.com/equity/82681/GFSTEELS/grand-foundry-ltd)\n- Grand Foundry Ltd share price | About Grand Foundry | Key Insights - Screener (https://www.screener.in/company/GFSTEELS)\n- Grand Foundry Ltd. (https://www.nirmalbang.com/company/grand-foundry/113343)\n- GFSTEELS Share Price Live Today: Grand Foundry NSE ... (https://www.tickertape.in/stocks/grand-foundry-GRND)\n- Grand Foundry Limited (INE534A01028) (https://www.nseindia.com/get-quote/equity/GFSTEELS/Grand-Foundry-Limited)\n- Grand Foundry Ltd Share Price Today : GFSTEELS Stock Price Live NSE/BSE | Torus Digital (https://www.torusdigital.com/stocks/grand-foundry-ltd-share-price)",
  "earnings": "",
  "analyst": "",
  "profile": "",
  "macro": {
    "fred": "============================================================\nGLOBAL MACRO INDICATORS  (Source: FRED — Federal Reserve)\nAs of 13 July 2026\n============================================================\n\nBrent Crude Oil [2026-07-06]\n  Current: 69.56 USD/bbl  (+1.28% vs prior)\n  India impact: Higher crude → India CAD widens, rupee weakens, oil companies pressured; lower crude → opposite\n\nUS Dollar Index (DXY) [2026-07-02]\n  Current: 120.69  (-0.38% vs prior)\n  India impact: Stronger DXY → FII outflows from India, rupee weakens; weaker DXY → FII inflows rise\n\nFed Funds Rate [2026-07-09]\n  Current: 3.62 %  (+0.00% vs prior)\n  India impact: Higher Fed rate → capital flows to USD, EM selling pressure; cuts → EM relief rally\n\nCBOE VIX [2026-07-09]\n  Current: 15.84  (-6.27% vs prior)\n  India impact: High VIX → risk-off, FII sell EMs including India; low VIX → risk-on, inflows\n\nUS 10Y Treasury Yield [2026-06-01]\n  Current: 4.47 %\n  India impact: Rising US 10Y → India bonds less attractive, FII debt outflows; falling → inflows\n\nYield Curve (10Y-2Y) [2026-07-10]\n  Current: 0.35 %  (-7.89% vs prior)\n  India impact: Negative spread = inverted curve = US recession risk → global risk-off, India hit\n\n============================================================",
    "india": "============================================================\nINDIA MACRO DATA  (Sources: NSE, RBI, yfinance)\nAs of 13 July 2026\n============================================================\n\n[MARKET RATES]\n  USD/INR           : Rs.95.63  (+0.28% — rupee weaker vs USD)\n  India impact      : Weaker rupee raises import costs, pressures CAD, may deter FII inflows\n  Nifty 50          : 24,193.90  (-0.07% today)\n\n[RBI MONETARY POLICY]\n  Repo Rate         : 6.25% (last known)\n  SDF (floor)       : 6.00%\n  MSF / Bank Rate   : 6.50%\n  CRR               : 4.00%\n  Stance            : Neutral\n  Last updated      : fallback as of Jul 2026\n  India impact      : Repo at 6.25% — accommodative relative to historic norms; supports credit growth\n\n[FII / DII DAILY FLOWS — Cash Market]\n  Data unavailable — NSE session could not be established\n  (Check NSE website directly for FII/DII flows)\n\n============================================================",
    "world_bank": "World Bank (latest annual):\n  Real GDP growth %: World 2.9% (2025)\n  Inflation (CPI) %: World 3.0% (2025)",
    "finnhub": ""
  }
}