{
  "ticker": "NESTLEIND.NS",
  "company": "Nestlé India Limited",
  "date": "2026-07-22",
  "generated_at_utc": "2026-07-22T07:34:24.416210+00:00",
  "fmp": "============================================================\nVERIFIED FUNDAMENTAL DATA  (Source: Financial Modeling Prep)\n============================================================\n\n============================================================",
  "screener": "=== Screener.in: NESTLEIND ===\nAbout: \nQuarterly Results (last 4Q — Sep 2025 / Dec 2025 / Mar 2026 / Jun 2026):\n  Sales +: 5,644 | 5,667 | 6,748 | 6,378\n  Net Profit +: 743 | 998 | 1,111 | 959\n  EPS in Rs: 3.85 | 5.18 | 5.76 | 4.97\nAnnual P&L (Dec 2023 / Mar 2024 15m / Mar 2025 / Mar 2026 / TTM):\n  Sales +: 19,126 | 24,394 | 20,202 | 23,155 | 24,437\n  OPM %: 23% | 24% | 24% | 23% | 23%\n  Net Profit +: 2,999 | 3,933 | 3,208 | 3,499 | 3,811\n  EPS in Rs: 15.55 | 20.40 | 16.63 | 18.15 | 19.76\nBalance Sheet (last 3 years):\n  Reserves: 3,244 | 3,914 | 4,964\n  Borrowings +: 345 | 1,167 | 444\n  Total Assets: 10,523 | 12,193 | 13,182\nShareholding Pattern (latest):\n  Promoters +: 62.76%\n  FIIs +: 10.30% (prev: 9.74%)\n  DIIs +: 11.89% (prev: 12.40%)\n  Public +: 15.04% (prev: 15.09%)",
  "yfinance": "=== yfinance Fundamentals: NESTLEIND.NS ===\nProfile: Sector=Consumer Defensive | Industry=Packaged Foods | Exchange=NSI | 52W=[Rs1,085–Rs1,510] | AvgVol=2,138,474\nAnalyst: Target(mean)=Rs1,482 | Target(high)=Rs1,675 | Target(low)=Rs1,265 | Consensus=Buy | Analysts=36\nValuation: P/E (TTM)=82.13x | P/E (Fwd)=62.40x | P/B=55.53x | EV/EBITDA=54.08x | EV/Revenue=12.07x\nEarnings: EPS (TTM)=Rs18.08 | EPS (Fwd)=Rs23.80 | EPS Growth=27.40% | Rev Growth=23.00%\nProfitability: Gross Margin=54.56% | Op Margin=22.96% | Net Margin=15.14% | ROE=76.34% | ROA=22.58%\nBalance Sheet: D/E=0.09x | Current Ratio=0.96x | Quick Ratio=0.35x | Free CF=Rs3,881 Cr | Op CF=Rs5,048 Cr\nMarket: Mkt Cap=Rs286,355 Cr | Ent Value=Rs279,096 Cr | Beta=0.44x | Div Yield=83.00%\nBusiness: Nestlé India Limited engages in the manufacture and sale of food products in India and internationally. It offers milk products and nutrition, including dairy whitener, condensed milk, UHT milk, yogurt, maternal and infant formula, baby foods, health care nutrition; prepared dishes and cooking aids, such as noodles, sauces, seasonings, pasta, cerea…",
  "announcements": "",
  "news_yf": "[2026-07-22] India's FMCG sector faces margin squeeze as costs spike amid strong demand, price hikes\n[2026-04-21] Nestle India profit jumps 26% on strong demand, shares rise\n[2026-01-30] Nestle India profit jumps 46% as tax cuts boost packaged food demand\n[2026-01-16] Nestle India names insider Edouard Mac Nab new CFO\n[2025-12-10] Nestle India's finance chief to step down\n[2025-10-17] Earnings, demand rebound hopes lift India's Nifty to one-year high",
  "news_web": "",
  "earnings": "",
  "analyst": "",
  "profile": "",
  "macro": {
    "fred": "============================================================\nGLOBAL MACRO INDICATORS  (Source: FRED — Federal Reserve)\nAs of 22 July 2026\n============================================================\n\nBrent Crude Oil [2026-07-13]\n  Current: 81.62 USD/bbl  (+9.79% vs prior)\n  India impact: Higher crude → India CAD widens, rupee weakens, oil companies pressured; lower crude → opposite\n\nUS Dollar Index (DXY) [2026-07-17]\n  Current: 120.53  (+0.17% vs prior)\n  India impact: Stronger DXY → FII outflows from India, rupee weakens; weaker DXY → FII inflows rise\n\nFed Funds Rate [2026-07-20]\n  Current: 3.63 %  (+0.00% vs prior)\n  India impact: Higher Fed rate → capital flows to USD, EM selling pressure; cuts → EM relief rally\n\nCBOE VIX [2026-07-20]\n  Current: 18.65  (-0.64% vs prior)\n  India impact: High VIX → risk-off, FII sell EMs including India; low VIX → risk-on, inflows\n\nUS 10Y Treasury Yield [2026-06-01]\n  Current: 4.47 %\n  India impact: Rising US 10Y → India bonds less attractive, FII debt outflows; falling → inflows\n\nYield Curve (10Y-2Y) [2026-07-21]\n  Current: 0.37 %  (-5.13% vs prior)\n  India impact: Negative spread = inverted curve = US recession risk → global risk-off, India hit\n\n============================================================",
    "india": "============================================================\nINDIA MACRO DATA  (Sources: NSE, RBI, yfinance)\nAs of 22 July 2026\n============================================================\n\n[MARKET RATES]\n  USD/INR           : Rs.96.49  (+0.28% — rupee weaker vs USD)\n  India impact      : Weaker rupee raises import costs, pressures CAD, may deter FII inflows\n  Nifty 50          : 23,989.00  (-0.85% today)\n\n[RBI MONETARY POLICY]\n  Repo Rate         : 6.25% (last known)\n  SDF (floor)       : 6.00%\n  MSF / Bank Rate   : 6.50%\n  CRR               : 4.00%\n  Stance            : Neutral\n  Last updated      : fallback as of Jul 2026\n  India impact      : Repo at 6.25% — accommodative relative to historic norms; supports credit growth\n\n[FII / DII DAILY FLOWS — Cash Market]\n  Data unavailable — NSE session could not be established\n  (Check NSE website directly for FII/DII flows)\n\n============================================================",
    "world_bank": "World Bank (latest annual):\n  Real GDP growth %: World 2.9% (2025)\n  Inflation (CPI) %: US 2.9% (2024)",
    "finnhub": ""
  }
}