{
  "ticker": "NRL.NS",
  "company": "Nupur Recyclers Limited",
  "date": "2026-07-04",
  "generated_at_utc": "2026-07-04T06:53:46.372609+00:00",
  "fmp": "============================================================\nVERIFIED FUNDAMENTAL DATA  (Source: Financial Modeling Prep)\n============================================================\n\n============================================================",
  "screener": "=== Screener.in: NRL ===\nAbout: \nQuarterly Results (last 4Q — Jun 2025 / Sep 2025 / Dec 2025 / Mar 2026):\n  Sales +: 50.99 | 48.76 | 58.88 | 57.32\n  Net Profit +: 4.05 | 4.33 | 4.76 | 3.34\n  EPS in Rs: 0.52 | 0.56 | 0.58 | 0.40\nAnnual P&L ( / Mar 2023 / Mar 2024 / Mar 2025 / Mar 2026):\n  Sales +: 187 | 240 | 158 | 216\n  OPM %: 7% | 3% | 10% | 8%\n  Net Profit +: 15 | 9 | 16 | 16\n  EPS in Rs: 1.78 | 1.05 | 2.11 | 2.06\nBalance Sheet (last 3 years):\n  Reserves: 17 | 49 | 65\n  Borrowings +: 13 | 13 | 33\n  Total Assets: 115 | 144 | 198\nShareholding Pattern (latest):\n  Promoters +: 73.13% (prev: 73.02%)\n  FIIs +: 0.00% (prev: 0.06%)\n  DIIs +: 0.00%\n  Public +: 26.87% (prev: 26.92%)",
  "yfinance": "=== yfinance Fundamentals: NRL.NS ===\nProfile: Sector=Industrials | Industry=Waste Management | Exchange=NSI | 52W=[Rs45–Rs93] | AvgVol=112,710\nAnalyst: Consensus=None\nValuation: P/E (TTM)=44.94x | P/B=4.79x | EV/EBITDA=39.89x | EV/Revenue=3.15x\nEarnings: EPS (TTM)=Rs2.06 | EPS Growth=33.30% | Rev Growth=54.00%\nProfitability: Gross Margin=15.35% | Op Margin=3.64% | Net Margin=6.58% | ROE=12.08% | ROA=4.91%\nBalance Sheet: D/E=0.23x | Current Ratio=5.28x | Quick Ratio=1.22x | Free CF=Rs-20 Cr | Op CF=Rs18 Cr\nMarket: Mkt Cap=Rs639 Cr | Ent Value=Rs681 Cr | Beta=0.34x\nBusiness: Nupur Recyclers Limited engages in the import, processing, and trading of ferrous and non-ferrous metals in India. The company imports metal scrap, such as shredded zinc scrap and brass, zinc die cast scrap, Zurik scrap, and aluminium zorba grades. It is also involved in the manufacture and trade of metals. The company was incorporated in 2019 and …",
  "announcements": "",
  "news_yf": "",
  "news_web": "- Nupur Recyclers Ltd. Share Price Today: Live updates (https://zerodha.com/markets/stocks/NSE/NRL)\n- Nupur Recyclers Ltd Results 2025: Nupur Recyclers Ltd Q4 Results & Revenue (https://www.indmoney.com/stocks/nupur-recyclers-ltd-share-price/results)\n- Nupur Recyclers Limited Share Price Today Live NSE/BSE (https://www.bajajfinserv.in/investments/nrl-share-price)\n- Nupur Recyclers Limited (https://nsearchives.nseindia.com/corporate/NRL_14112022172254_OUTCOMEOFTHEBOARDMEETINGFINAL1.pdf)\n- Nupur Recyclers - NRL corporate action history (https://trendlyne.com/equity/corporate-actions/NRL/750562/nupur-recyclers-ltd)\n- Nupur Recyclers Share Price - MarketSmith India (https://marketsmithindia.com/mstool/eval/list/nrl/evaluation.jsp)",
  "earnings": "",
  "analyst": "",
  "profile": "",
  "macro": {
    "fred": "============================================================\nGLOBAL MACRO INDICATORS  (Source: FRED — Federal Reserve)\nAs of 04 July 2026\n============================================================\n\nBrent Crude Oil [2026-06-29]\n  Current: 71.59 USD/bbl  (+2.04% vs prior)\n  India impact: Higher crude → India CAD widens, rupee weakens, oil companies pressured; lower crude → opposite\n\nUS Dollar Index (DXY) [2026-06-26]\n  Current: 120.89  (-0.14% vs prior)\n  India impact: Stronger DXY → FII outflows from India, rupee weakens; weaker DXY → FII inflows rise\n\nFed Funds Rate [2026-07-01]\n  Current: 3.63 %  (+0.00% vs prior)\n  India impact: Higher Fed rate → capital flows to USD, EM selling pressure; cuts → EM relief rally\n\nCBOE VIX [2026-07-01]\n  Current: 16.59  (+0.85% vs prior)\n  India impact: High VIX → risk-off, FII sell EMs including India; low VIX → risk-on, inflows\n\nUS 10Y Treasury Yield [2026-06-01]\n  Current: 4.47 %\n  India impact: Rising US 10Y → India bonds less attractive, FII debt outflows; falling → inflows\n\nYield Curve (10Y-2Y) [2026-07-02]\n  Current: 0.35 %  (+12.90% vs prior)\n  India impact: Negative spread = inverted curve = US recession risk → global risk-off, India hit\n\n============================================================",
    "india": "============================================================\nINDIA MACRO DATA  (Sources: NSE, RBI, yfinance)\nAs of 04 July 2026\n============================================================\n\n[MARKET RATES]\n  USD/INR           : Rs.95.20  (-0.19% — rupee stronger vs USD)\n  India impact      : Stronger rupee reduces import costs, supports FII inflows\n  Nifty 50          : 24,270.85  (+0.43% today)\n\n[RBI MONETARY POLICY]\n  Repo Rate         : 6.25% (last known)\n  SDF (floor)       : 6.00%\n  MSF / Bank Rate   : 6.50%\n  CRR               : 4.00%\n  Stance            : Neutral\n  Last updated      : fallback as of Jul 2026\n  India impact      : Repo at 6.25% — accommodative relative to historic norms; supports credit growth\n\n[FII / DII DAILY FLOWS — Cash Market]\n  Data unavailable — NSE session could not be established\n  (Check NSE website directly for FII/DII flows)\n\n============================================================",
    "world_bank": "World Bank (latest annual):\n  Real GDP growth %: India 7.6% (2025) · World 2.9% (2025)\n  Inflation (CPI) %: India 2.4% (2025) · World 3.0% (2025)",
    "finnhub": ""
  }
}