{
  "ticker": "RELINFRA.NS",
  "company": "Reliance Infrastructure Limited",
  "date": "2026-07-20",
  "generated_at_utc": "2026-07-20T08:06:22.360166+00:00",
  "fmp": "============================================================\nVERIFIED FUNDAMENTAL DATA  (Source: Financial Modeling Prep)\n============================================================\n\n============================================================",
  "screener": "=== Screener.in: RELINFRA ===\nAbout: \nQuarterly Results (last 4Q — Jun 2025 / Sep 2025 / Dec 2025 / Mar 2026):\n  Sales +: 5,908 | 6,235 | 4,297 | 4,001\n  Net Profit +: 305 | 2,575 | 317 | 1,640\n  EPS in Rs: 1.46 | 46.77 | 0.27 | 22.47\nAnnual P&L (Mar 2022 / Mar 2023 / Mar 2024 / Mar 2025 / Mar 2026):\n  Sales +: 19,689 | 22,398 | 22,805 | 24,441 | 20,441\n  OPM %: 9% | 6% | 9% | 15% | 5%\n  Net Profit +: -868 | -2,564 | -1,148 | 9,177 | 4,838\n  EPS in Rs: -37.98 | -91.57 | -40.61 | 124.64 | 70.97\nBalance Sheet (last 3 years):\n  Reserves: 8,351 | 14,034 | 17,464\n  Borrowings +: 9,895 | 6,361 | 4,937\n  Total Assets: 59,159 | 65,841 | 71,160\nShareholding Pattern (latest):\n  Promoters +: 19.05%\n  FIIs +: 4.94% (prev: 5.53%)\n  DIIs +: 0.78% (prev: 1.24%)\n  Government +: 0.01%",
  "yfinance": "=== yfinance Fundamentals: RELINFRA.NS ===\nProfile: Sector=Utilities | Industry=Utilities - Independent Power Producers | Exchange=NSI | 52W=[Rs63–Rs392] | AvgVol=223,069\nAnalyst: Consensus=None\nValuation: P/E (TTM)=0.88x | P/B=0.14x | EV/EBITDA=6.23x | EV/Revenue=0.81x\nEarnings: EPS (TTM)=Rs71.41 | EPS Growth=-73.30% | Rev Growth=-2.60%\nProfitability: Gross Margin=29.15% | Op Margin=-16.77% | Net Margin=14.19% | ROE=18.29% | ROA=1.08%\nBalance Sheet: D/E=0.17x | Current Ratio=0.21x | Quick Ratio=0.11x | Free CF=Rs1,270 Cr | Op CF=Rs2,550 Cr\nMarket: Mkt Cap=Rs2,576 Cr | Ent Value=Rs16,515 Cr | Beta=0.68x\nBusiness: Reliance Infrastructure Limited, an infrastructure company, generates, transmits, and distributes electrical power to residential, industrial, commercial, and other consumers in India. It operates through three segments: Power; Engineering and Construction (E&C); and Infrastructure. The Power segment engages in the operation of 220 megawatts of com…",
  "announcements": "",
  "news_yf": "[2025-11-03] Indian financial crimes agency freezes Anil Ambani Group properties worth $853 million\n[2025-09-30] Reliance Infra says financial crime agency's search linked to toll road deal, not forex\n[2025-09-05] Dassault Aviation buys 2% stake in JV with Anil Ambani's Reliance, taking majority control\n[2025-08-24] India's Reliance Infra, Reliance Power say no impact from criminal case against Anil Ambani\n[2025-08-08] India's Reliance Infra to recover $3.25 billion in unpaid power dues from New Delhi consumers",
  "news_web": "",
  "earnings": "",
  "analyst": "",
  "profile": "",
  "macro": {
    "fred": "============================================================\nGLOBAL MACRO INDICATORS  (Source: FRED — Federal Reserve)\nAs of 20 July 2026\n============================================================\n\nBrent Crude Oil [2026-07-13]\n  Current: 81.62 USD/bbl  (+9.79% vs prior)\n  India impact: Higher crude → India CAD widens, rupee weakens, oil companies pressured; lower crude → opposite\n\nUS Dollar Index (DXY) [2026-07-10]\n  Current: 120.50  (-0.21% vs prior)\n  India impact: Stronger DXY → FII outflows from India, rupee weakens; weaker DXY → FII inflows rise\n\nFed Funds Rate [2026-07-16]\n  Current: 3.63 %  (+0.00% vs prior)\n  India impact: Higher Fed rate → capital flows to USD, EM selling pressure; cuts → EM relief rally\n\nCBOE VIX [2026-07-16]\n  Current: 16.73  (+6.76% vs prior)\n  India impact: High VIX → risk-off, FII sell EMs including India; low VIX → risk-on, inflows\n\nUS 10Y Treasury Yield [2026-06-01]\n  Current: 4.47 %\n  India impact: Rising US 10Y → India bonds less attractive, FII debt outflows; falling → inflows\n\nYield Curve (10Y-2Y) [2026-07-17]\n  Current: 0.37 %  (-9.76% vs prior)\n  India impact: Negative spread = inverted curve = US recession risk → global risk-off, India hit\n\n============================================================",
    "india": "============================================================\nINDIA MACRO DATA  (Sources: NSE, RBI, yfinance)\nAs of 20 July 2026\n============================================================\n\n[MARKET RATES]\n  USD/INR           : Rs.96.39  (+0.13% — rupee weaker vs USD)\n  India impact      : Weaker rupee raises import costs, pressures CAD, may deter FII inflows\n  Nifty 50          : 24,245.60  (-0.40% today)\n\n[RBI MONETARY POLICY]\n  Repo Rate         : 6.25% (last known)\n  SDF (floor)       : 6.00%\n  MSF / Bank Rate   : 6.50%\n  CRR               : 4.00%\n  Stance            : Neutral\n  Last updated      : fallback as of Jul 2026\n  India impact      : Repo at 6.25% — accommodative relative to historic norms; supports credit growth\n\n[FII / DII DAILY FLOWS — Cash Market]\n  Data unavailable — NSE session could not be established\n  (Check NSE website directly for FII/DII flows)\n\n============================================================",
    "world_bank": "World Bank (latest annual):\n  Real GDP growth %: India 7.6% (2025) · US 2.2% (2025) · World 2.9% (2025)\n  Inflation (CPI) %: India 2.4% (2025) · US 2.9% (2024) · World 3.0% (2025)",
    "finnhub": ""
  }
}